texttotest/__init__.py
texttotest/generate.py
texttotest-0.0.1.dist-info/LICENSE
texttotest-0.0.1.dist-info/METADATA
texttotest-0.0.1.dist-info/WHEEL
texttotest-0.0.1.dist-info/top_level.txt
texttotest-0.0.1.dist-info/RECORD
