Metadata-Version: 2.1
Name: texttotest
Version: 0.0.1
Summary: A Python package to create tests from text file
Home-page: https://github.com/djumanovdev/texttotest
Author: djumanovdev
Author-email: djumanovdev@gmail.com
License: MIT
Platform: UNKNOWN
Requires-Python: >=3.8
License-File: LICENSE
